{
  "pagination": {
    "page": 1,
    "pages": 71,
    "per_page": 5,
    "items": 354,
    "urls": {
      "last": "https://api.discogs.com/database/search?q=Pulp+Fiction+soundtrack&type=release&per_page=5&key=woTphKEaoIPOYHLyYhlp&secret=ODdqgEESNliJmkOHZtsEqxurdzcgNyRL&page=71",
      "next": "https://api.discogs.com/database/search?q=Pulp+Fiction+soundtrack&type=release&per_page=5&key=woTphKEaoIPOYHLyYhlp&secret=ODdqgEESNliJmkOHZtsEqxurdzcgNyRL&page=2"
    }
  },
  "results": [
    {
      "country": "Europe",
      "year": "2008",
      "format": [
        "Vinyl",
        "LP",
        "Compilation",
        "Reissue",
        "Remastered"
      ],
      "label": [
        "MCA Records",
        "Back To Black",
        "MCA Records, Inc.",
        "PolyGram Inc.",
        "Touch And Go Records",
        "Geffen Records, Inc.",
        "Downey Records",
        "PolyGram Records, Inc.",
        "MCA Records, Inc.",
        "Miramax Films",
        "CEMA Special Markets",
        "Matragun Music, Inc.",
        "EMI Unart Catalog Inc.",
        "Universal Music Group International",
        "Future Disc",
        "GZ Digital Media",
        "www.gzvinyl.com"
      ],
      "type": "release",
      "genre": [
        "Rock",
        "Funk / Soul",
        "Non-Music",
        "Stage & Screen"
      ],
      "style": [
        "Surf",
        "Rock & Roll",
        "Dialogue",
        "Soul",
        "Soundtrack",
        "Funk"
      ],
      "id": 2068953,
      "barcode": [
        "0 08811 11031 4",
        "008811110314",
        "LC 01056",
        "BIEM/SABAM",
        "BMI",
        "ASCAP",
        "B2BSTK",
        "B2BVCHR",
        "91848E1/B www.gzvinyl.com-1111031-A",
        "91848E2/A 1111031-B",
        "91848E1/B www.gzvinyl.com-1111031-A",
        "91848E2/B 1111031-B",
        "91848E1/C www.gzvinyl.com-1111031-A",
        "91848E2/C 1111031-B",
        "91848E1/C www.gzvinyl.com-1111031-A",
        "91848E2/E 1111031-B"
      ],
      "master_id": 17468,
      "master_url": "https://api.discogs.com/masters/17468",
      "uri": "/release/2068953-Various-Pulp-Fiction-Music-From-The-Motion-Picture",
      "catno": "0008811110314",
      "title": "Various - Pulp Fiction (Music From The Motion Picture)",
      "thumb": "https://i.discogs.com/KbppDgf2B9CLS-j2DF8hb9hm9RcgkWX7QczOOC3k5zw/rs:fit/g:sm/q:40/h:150/w:150/czM6Ly9kaXNjb2dz/LWRhdGFiYXNlLWlt/YWdlcy9SLTIwNjg5/NTMtMTY0MTA1OTc5/MC00MDAzLmpwZWc.jpeg",
      "cover_image": "https://i.discogs.com/bMEU1aKZsTrPRzJ9FkWvBE18G_AuN21CmAt8jjtJLdY/rs:fit/g:sm/q:90/h:600/w:600/czM6Ly9kaXNjb2dz/LWRhdGFiYXNlLWlt/YWdlcy9SLTIwNjg5/NTMtMTY0MTA1OTc5/MC00MDAzLmpwZWc.jpeg",
      "resource_url": "https://api.discogs.com/releases/2068953",
      "community": {
        "want": 3865,
        "have": 18808
      },
      "format_quantity": 1,
      "formats": [
        {
          "name": "Vinyl",
          "qty": "1",
          "text": "180 Gram",
          "descriptions": [
            "LP",
            "Compilation",
            "Reissue",
            "Remastered"
          ]
        }
      ]
    },
    {
      "country": "Spain",
      "year": "2006",
      "format": [
        "Vinyl",
        "LP",
        "Compilation",
        "Picture Disc",
        "Reissue"
      ],
      "label": [
        "Esmerilla Records"
      ],
      "type": "release",
      "genre": [
        "Rock",
        "Funk / Soul",
        "Non-Music",
        "Stage & Screen"
      ],
      "style": [
        "Surf",
        "Rock & Roll",
        "Dialogue",
        "Soul",
        "Soundtrack",
        "Funk"
      ],
      "id": 1146038,
      "barcode": [
        "5 038656 283619",
        "PFPD 1017 A 2",
        "PFPD 1017 B 1"
      ],
      "master_id": 17468,
      "master_url": "https://api.discogs.com/masters/17468",
      "uri": "/release/1146038-Various-Pulp-Fiction-Music-From-The-Original-Motion-Picture-Soundtrack-Collectors-Edition",
      "catno": "PFPD 1017",
      "title": "Various - Pulp Fiction - Music From The Original Motion Picture Soundtrack (Collector's Edition)",
      "thumb": "https://i.discogs.com/Z6304BJsSzovfy2-98yJlT5O54sFrtE1klvbG_fT2PA/rs:fit/g:sm/q:40/h:150/w:150/czM6Ly9kaXNjb2dz/LWRhdGFiYXNlLWlt/YWdlcy9SLTExNDYw/MzgtMTY2MzM0Nzk3/MS04MDE1LmpwZWc.jpeg",
      "cover_image": "https://i.discogs.com/DUe3EBUI4fGuVl5oCdbL8wkQXcQzlrLNCt6BWAgdU84/rs:fit/g:sm/q:90/h:600/w:600/czM6Ly9kaXNjb2dz/LWRhdGFiYXNlLWlt/YWdlcy9SLTExNDYw/MzgtMTY2MzM0Nzk3/MS04MDE1LmpwZWc.jpeg",
      "resource_url": "https://api.discogs.com/releases/1146038",
      "community": {
        "want": 668,
        "have": 310
      },
      "format_quantity": 1,
      "formats": [
        {
          "name": "Vinyl",
          "qty": "1",
          "descriptions": [
            "LP",
            "Compilation",
            "Picture Disc",
            "Reissue"
          ]
        }
      ]
    },
    {
      "country": "Europe",
      "genre": [
        "Rock",
        "Funk / Soul",
        "Non-Music",
        "Pop",
        "Stage & Screen"
      ],
      "format": [
        "Vinyl",
        "LP",
        "Album",
        "Compilation",
        "Reissue",
        "Remastered"
      ],
      "style": [
        "Surf",
        "Rock & Roll",
        "Dialogue",
        "Soul",
        "Soundtrack",
        "Funk"
      ],
      "id": 7040876,
      "label": [
        "MCA Records",
        "Back To Black",
        "Universal International Music B.V.",
        "MCA Records, Inc.",
        "MCA Records, Inc.",
        "Miramax Films",
        "Future Disc",
        "Takt Direct"
      ],
      "type": "release",
      "barcode": [
        "0 08811 11031 4",
        "LC 01056",
        "BIEM/SABAM",
        "0931528-A-1 21",
        "0931528-B-1 71",
        "0931528-A-1 18 2",
        "0931528-B-1 2"
      ],
      "master_id": 17468,
      "master_url": "https://api.discogs.com/masters/17468",
      "uri": "/release/7040876-Various-Pulp-Fiction-Music-From-The-Motion-Picture",
      "catno": "0008811110314",
      "title": "Various - Pulp Fiction (Music From The Motion Picture)",
      "thumb": "https://i.discogs.com/TPlNtZpdLvntGLZdV3bIM47Avt9u0x2v0eB0955c8v4/rs:fit/g:sm/q:40/h:150/w:150/czM6Ly9kaXNjb2dz/LWRhdGFiYXNlLWlt/YWdlcy9SLTcwNDA4/NzYtMTY1Njk3NjI2/Ni0yMDc1LmpwZWc.jpeg",
      "cover_image": "https://i.discogs.com/BWisOHgMA_cJ4jc0Md-bAIUk5RuSo_Idoa7bRtaFMkw/rs:fit/g:sm/q:90/h:600/w:600/czM6Ly9kaXNjb2dz/LWRhdGFiYXNlLWlt/YWdlcy9SLTcwNDA4/NzYtMTY1Njk3NjI2/Ni0yMDc1LmpwZWc.jpeg",
      "resource_url": "https://api.discogs.com/releases/7040876",
      "community": {
        "want": 1178,
        "have": 13164
      },
      "format_quantity": 1,
      "formats": [
        {
          "name": "Vinyl",
          "qty": "1",
          "text": "180 Gram",
          "descriptions": [
            "LP",
            "Album",
            "Compilation",
            "Reissue",
            "Remastered"
          ]
        }
      ]
    },
    {
      "country": "US",
      "year": "1994",
      "format": [
        "Vinyl",
        "LP",
        "Album",
        "Compilation"
      ],
      "label": [
        "MCA Records",
        "MCA Records, Inc.",
        "MCA Records, Inc.",
        "Uni Distribution Corp.",
        "Future Disc"
      ],
      "type": "release",
      "genre": [
        "Rock",
        "Funk / Soul",
        "Non-Music",
        "Stage & Screen"
      ],
      "style": [
        "Surf",
        "Rock & Roll",
        "Dialogue",
        "Soul",
        "Soundtrack",
        "Funk"
      ],
      "id": 376354,
      "barcode": [
        "0 08811 11031 4",
        "008811110314",
        "MCA 12066-FDS 2  KPG",
        "MCA 12067-FDS 1"
      ],
      "master_id": 17468,
      "master_url": "https://api.discogs.com/masters/17468",
      "uri": "/release/376354-Various-Pulp-Fiction-Music-From-The-Motion-Picture",
      "catno": "MCA-11103",
      "title": "Various - Pulp Fiction (Music From The Motion Picture)",
      "thumb": "https://i.discogs.com/dM3cEFhZE8hDnMF3u1Ggm22tGhMhheM-HDel8y4SZig/rs:fit/g:sm/q:40/h:150/w:150/czM6Ly9kaXNjb2dz/LWRhdGFiYXNlLWlt/YWdlcy9SLTM3NjM1/NC0xNTkxNTYwMzMz/LTQ3MzAuanBlZw.jpeg",
      "cover_image": "https://i.discogs.com/2qTMmxHghCkx8T10Jd5VebocT61oxLUsYcE8awOyzGg/rs:fit/g:sm/q:90/h:594/w:600/czM6Ly9kaXNjb2dz/LWRhdGFiYXNlLWlt/YWdlcy9SLTM3NjM1/NC0xNTkxNTYwMzMz/LTQ3MzAuanBlZw.jpeg",
      "resource_url": "https://api.discogs.com/releases/376354",
      "community": {
        "want": 2879,
        "have": 8114
      },
      "format_quantity": 1,
      "formats": [
        {
          "name": "Vinyl",
          "qty": "1",
          "descriptions": [
            "LP",
            "Album",
            "Compilation"
          ]
        }
      ]
    },
    {
      "country": "Europe",
      "year": "1994",
      "format": [
        "Vinyl",
        "LP",
        "Compilation",
        "Stereo"
      ],
      "label": [
        "MCA Records",
        "Future Disc",
        "PMDC, Germany",
        "PMDC, Germany",
        "Matragun Music, Inc.",
        "EMI Unart Catalog Inc.",
        "CEMA Special Markets",
        "Polygram Special Markets",
        "Rhino Records",
        "Warner Special Products",
        "Polygram Record Operations Ltd.",
        "Uni Distribution Corp.",
        "PolyGram Inc.",
        "Touch And Go Records",
        "Geffen Records, Inc.",
        "MCA Records, Inc.",
        "MCA Records, Inc."
      ],
      "type": "release",
      "genre": [
        "Rock",
        "Funk / Soul",
        "Non-Music",
        "Stage & Screen"
      ],
      "style": [
        "Surf",
        "Rock & Roll",
        "Dialogue",
        "Soul",
        "Soundtrack",
        "Funk",
        "Indie Rock",
        "Rockabilly",
        "Score"
      ],
      "id": 654018,
      "barcode": [
        "0 008811 110314",
        "LC 01056",
        "BIEM/MCPS",
        "D33 111 103-1 S1 320",
        "D33 111 103-1 S2 320"
      ],
      "master_id": 17468,
      "master_url": "https://api.discogs.com/masters/17468",
      "uri": "/release/654018-Various-Pulp-Fiction-Music-From-The-Motion-Picture",
      "catno": "111 103-1",
      "title": "Various - Pulp Fiction (Music From The Motion Picture)",
      "thumb": "https://i.discogs.com/WE7JuCoKozSfmlvE0D6y_7huPAPYO5tV0eW-kohcoko/rs:fit/g:sm/q:40/h:150/w:150/czM6Ly9kaXNjb2dz/LWRhdGFiYXNlLWlt/YWdlcy9SLTY1NDAx/OC0xNjUyOTc4Mzkx/LTYyMjcuanBlZw.jpeg",
      "cover_image": "https://i.discogs.com/9sUL1Tq8CfJGILvakiwnqHQa8CGe3g6ONPJkDMwKAsQ/rs:fit/g:sm/q:90/h:600/w:600/czM6Ly9kaXNjb2dz/LWRhdGFiYXNlLWlt/YWdlcy9SLTY1NDAx/OC0xNjUyOTc4Mzkx/LTYyMjcuanBlZw.jpeg",
      "resource_url": "https://api.discogs.com/releases/654018",
      "community": {
        "want": 1792,
        "have": 7021
      },
      "format_quantity": 1,
      "formats": [
        {
          "name": "Vinyl",
          "qty": "1",
          "descriptions": [
            "LP",
            "Compilation",
            "Stereo"
          ]
        }
      ]
    }
  ]
}